fifam5tl/__init__.py
fifam5tl/main.py
fifam5tl-0.1.1.dist-info/METADATA
fifam5tl-0.1.1.dist-info/WHEEL
fifam5tl-0.1.1.dist-info/entry_points.txt
fifam5tl-0.1.1.dist-info/top_level.txt
fifam5tl-0.1.1.dist-info/RECORD
